[
  {
    "imageUrl": "./images/financeTracker.png",
    "title": "Finance Tracker Ai",
    "description": "A personal finance management application featuring a unique hand-drawn (paper) aesthetic. It goes beyond simple tracking by integrating Google Gemini AI to provide intelligent financial insights and personalized advice.",
    "viewUrl": "",
    "repoUrl": "https://github.com/farhandavin/FinanceTracker"
  },
  {
    "imageUrl": "./images/AiQuizGenerator.png",
    "title": "Ai Quiz Generator",
    "description": "A smart web application designed to automatically generate multiple-choice quizzes by analyzing uploaded study materials (PDF/Images) or raw text. This application is powered by Google Gemini AI to ensure high-quality question generation.",
    "viewUrl": "#",
    "repoUrl": "https://github.com/farhandavin/webBelajarAi?tab=readme-ov-file"
  }
]